{
  "project_info": {
    "project_number": "326837888335",
    "project_id": "scrapper-079",
    "storage_bucket": "scrapper-079.firebasestorage.app"
  },
  "client": [
    {
      "client_info": {
        "mobilesdk_app_id": "1:326837888335:android:2058464068770da6a2913a",
        "android_client_info": {
          "package_name": "com.example.scrapper"
        }
      },
      "oauth_client": [],
      "api_key": [
        {
          "current_key": "AIzaSyD7eObWdxcnI6wjWTaP6ip15fRAeRlv_Oo"
        }
      ],
      "services": {
        "appinvite_service": {
          "other_platform_oauth_client": []
        }
      }
    },
    {
      "client_info": {
        "mobilesdk_app_id": "1:326837888335:android:8099bb38ed57cee5a2913a",
        "android_client_info": {
          "package_name": "com.example.scrapper_partner"
        }
      },
      "oauth_client": [],
      "api_key": [
        {
          "current_key": "AIzaSyD7eObWdxcnI6wjWTaP6ip15fRAeRlv_Oo"
        }
      ],
      "services": {
        "appinvite_service": {
          "other_platform_oauth_client": []
        }
      }
    },
    {
      "client_info": {
        "mobilesdk_app_id": "1:326837888335:android:d7b6f3cc0f57b5e5a2913a",
        "android_client_info": {
          "package_name": "com.example.scrapper_sanitarian"
        }
      },
      "oauth_client": [],
      "api_key": [
        {
          "current_key": "AIzaSyD7eObWdxcnI6wjWTaP6ip15fRAeRlv_Oo"
        }
      ],
      "services": {
        "appinvite_service": {
          "other_platform_oauth_client": []
        }
      }
    }
  ],
  "configuration_version": "1"
}